Workbook

Sheet Inputs
A1: ClinFlow — Calculadora de Custos do WhatsApp (Meta)
A2: Preencha as tarifas oficiais em R$/mensagem e os volumes mensais por categoria. Ajuste o markup para simular o preço ao cliente.
A4: País | B4: Brasil | D4: Preço do Dolar | E4: 5.281
A5: Moeda | B5: BRL (R$)
A7: Tarifas da Meta (R$/mensagem entregue) — inserir valores oficiais
A8: Categoria | B8: Tarifa (U$) | C8: Tarifa (R$) | D8: Tarifa ClinFlow | E8: Volumes por cenário (mensal)
A9: Marketing | B9: 0.0625 | C9: =B9*$E$4 -> 0.3300625 | D9: =C9*$C$14 -> 0.660125 | E9: Cenário | F9: Categoria | G9: Qtde msgs
A10: Utilidade | B10: 0.0068 | C10: =B10*$E$4 -> 0.0359108 | D10: =C10*$C$14 -> 0.0718216 | E10: Baixo | F10: Marketing | G10: 500
A11: Autenticação | B11: 0.0068 | C11: =B11*$E$4 -> 0.0359108 | D11: =C11*$C$14 -> 0.0718216 | E11: Baixo | F11: Utilidade | G11: 2500
A12: Serviço (resposta em até 24h) | B12: 0 | C12: =B12*$E$4 -> 0 | E12: Baixo | F12: Autenticação | G12: 300
E13: Baixo | F13: Serviço | G13: 4000
A14: Markup do ClinFlow sobre o custo da Meta | C14: 2 | E14: Médio | F14: Marketing | G14: 3000
E15: Médio | F15: Utilidade | G15: 15000
A16: Custo dos pacotes | B16: Para o Clinflow | C16: Para o Cliente | E16: Médio | F16: Autenticação | G16: 1500
A17: 1000 | B17: =$C$10*A17 -> 35.9108 | E17: Médio | F17: Serviço | G17: 20000
A18: 2000 | B18: =$C$10*A18 -> 71.8216 | E18: Alto | F18: Marketing | G18: 10000
A19: 3000 | B19: =$C$10*A19 -> 107.7324 | E19: Alto | F19: Utilidade | G19: 60000
A20: 4000 | B20: =$C$10*A20 -> 143.6432 | E20: Alto | F20: Autenticação | G20: 5000
A21: 5000 | B21: =$C$10*A21 -> 179.554 | E21: Alto | F21: Serviço | G21: 80000
A22: 10000 | B22: =$C$10*A22 -> 359.108

Sheet Resultados
A1: Resultados por cenário (Base: R$/mensagem por categoria)
A3: Cenário | B3: Custo Meta — Marketing (R$) | C3: Custo Meta — Utilidade (R$) | D3: Custo Meta — Autenticação (R$) | E3: Custo Meta — Serviço (R$) | F3: Custo Meta Total (R$) | G3: Markup (%) | H3: Receita Bruta (R$) | I3: Margem (R$) | J3: Custo por Paciente (opcional)
A4: Baixo | F4: =SUM(B4:E4) -> 0 | G4: =Inputs!$B$14 -> 0 | H4: =F4*(1+G4) -> 0 | I4: =H4-F4 -> 0 | J4: =IF(Inputs!$B$16>0, F4/Inputs!$B$16, "-") -> #VALUE!
A5: Médio | F5: =SUM(B5:E5) -> 0 | G5: =Inputs!$B$14 -> 0 | H5: =F5*(1+G5) -> 0 | I5: =H5-F5 -> 0 | J5: =IF(Inputs!$B$16>0, F5/Inputs!$B$16, "-") -> #VALUE!
A6: Alto | F6: =SUM(B6:E6) -> 0 | G6: =Inputs!$B$14 -> 0 | H6: =F6*(1+G6) -> 0 | I6: =H6-F6 -> 0 | J6: =IF(Inputs!$B$16>0, F6/Inputs!$B$16, "-") -> #VALUE!

Sheet Notas
A1: Como usar:
A2: 1) Abra https://business.whatsapp.com/products/platform-pricing e selecione Brasil e a categoria. Copie a tarifa R$/mensagem e cole em Inputs!B9:B12.
A3: 2) Ajuste os volumes por cenário em Inputs (coluna F).
A4: 3) Ajuste o markup (Inputs!B14).
A5: 4) Veja os resultados em 'Resultados'. Revise sempre no site da Meta, pois valores mudam.
A7: Observações:
A8: • 'Serviço' (resposta dentro de 24h) é gratuito conforme página atual; confirme no dia do orçamento.
A9: • A Meta cobra mensagens entregues. Tarifas variam por categoria, país e podem ter faixas por volume (tiers).
A10: • Use templates aprovados fora da janela de 24h; 'Marketing' custa mais que 'Utilidade'.
